TaxSEA_in_python/TaxSEA.py
TaxSEA_in_python/__init__.py
TaxSEA_in_python/__main__.py
TaxSEA_in_python/get_IDs.py
TaxSEA_in_python/data/Local_NCBI_db.csv
TaxSEA_in_python/data/TaxSEA_DB.plk
TaxSEA_in_python/data/TaxSEA_test_data.csv
TaxSEA_in_python-0.1.4.dist-info/METADATA
TaxSEA_in_python-0.1.4.dist-info/WHEEL
TaxSEA_in_python-0.1.4.dist-info/entry_points.txt
TaxSEA_in_python-0.1.4.dist-info/top_level.txt
TaxSEA_in_python-0.1.4.dist-info/RECORD
