Metadata-Version: 2.2
Name: TaxSEA_in_python
Version: 0.1.4
Summary: A small package for converting bacterial names into NCBI IDs
Author-email: Cong Pham <phamleminhcong34@gmail.com>
Classifier: Programming Language :: Python :: 3
Classifier: License :: OSI Approved :: MIT License
Classifier: Operating System :: OS Independent
Requires-Python: >=3.8
Requires-Dist: pandas>=1.3.0
Requires-Dist: requests>=2.25.0
Requires-Dist: importlib-resources>=5.0.0
Requires-Dist: statsmodels>=0.14.4
Requires-Dist: numpy>=1.21.0
